jamspy/__init__.py
jamspy/client/__init__.py
jamspy/client/grpc.py
jamspy/client/http.py
jamspy/client/models/__init__.py
jamspy/client/models/common.py
jamspy/client/models/http.py
jamspy/client/models/proto/__init__.py
jamspy/client/models/proto/jams_pb2.py
jamspy/client/models/proto/jams_pb2.pyi
jamspy/client/models/proto/jams_pb2_grpc.py
jamspy/utils/__init__.py
jamspy/utils/bundler/__init__.py
jamspy/utils/bundler/catboost_model.py
jamspy/utils/bundler/common.py
jamspy/utils/bundler/lightgbm_model.py
jamspy/utils/bundler/pytorch_model.py
jamspy/utils/bundler/tensorflow_model.py
jamspy-0.4.0.dist-info/LICENSE
jamspy-0.4.0.dist-info/METADATA
jamspy-0.4.0.dist-info/WHEEL
jamspy-0.4.0.dist-info/top_level.txt
jamspy-0.4.0.dist-info/RECORD
