Metadata-Version: 2.1
Name: jamspy
Version: 0.4.0
Summary: A HTTP & gRPC client for J.A.M.S - Just Another Model Server in Python
Author: gagansingh894
Project-URL: Homepage, https://github.com/gagansingh894/jams-rs/tree/main/clients/python/jams
Requires-Python: >=3.9
License-File: LICENSE
Requires-Dist: pydantic ==2.6
Requires-Dist: requests ==2.32.3
Requires-Dist: grpcio ==1.67.0
Requires-Dist: protobuf >=3.20.3
Requires-Dist: grpcio-tools ==1.65.5
Requires-Dist: ruff ==0.6.9
Requires-Dist: mypy ==1.11.1
Requires-Dist: types-requests ==2.32.0.20240914
Requires-Dist: types-protobuf ==5.28.0.20240924
Requires-Dist: pytest ==8.0.0
Requires-Dist: pytest-asyncio ==0.23.8
Requires-Dist: nox ==2024.4.15
Requires-Dist: catboost ==1.2.3
Requires-Dist: lightgbm ==4.0.0
Requires-Dist: torch ==2.2.0
Requires-Dist: xgboost ==2.0.3
Requires-Dist: numpy ==1.26.0
Requires-Dist: httpx ==0.26.0
Provides-Extra: dev
Requires-Dist: check-manifest ; extra == 'dev'
